<?xml version = '1.0' encoding = 'UTF-8'?>
<FKIndexAssociation class="oracle.dbtools.crest.model.design.relational.FKIndexAssociation" directorySegmentName="seg_4" id="5CB19D1A-4554-73E5-DBEE-8F76A35B9207" containerWithKeyObject="5C5A2908-79CB-E42A-1975-72032DEF0786" localFKIndex="8F3D1ECE-0339-ACAE-22C8-BD0522C8CDA9" name="R_SST2_R_S_FK">
<sourceConnName>Oracle-RDS</sourceConnName>
<sourceObjSchema>ADMIN</sourceObjSchema>
<sourceObjName>R_SST2_R_S_FK</sourceObjName>
<createdBy>johan</createdBy>
<createdTime>2023-02-21 09:08:18 UTC</createdTime>
<ownerDesignName>ERD</ownerDesignName>
<importedID>33572AED-499C-EA12-3532-F8D43AE1A9E7</importedID>
<referredTableLongName>ADMIN.R_SOURCE</referredTableLongName>
<deleteRule>NO ACTION</deleteRule>
<referredTableID>7C785EAD-0860-691C-1778-D9CD14006EAE</referredTableID>
<keyObject>11947036-EC44-D015-F6FE-1104E016E341</keyObject>
<referredKeyID>11947036-EC44-D015-F6FE-1104E016E341</referredKeyID>
<mandatory>false</mandatory>
<refColNames>SOURCE</refColNames>
<transferable>true</transferable>
<rely>false</rely>
<columnDependencyConstraintGenerateInDDL>true</columnDependencyConstraintGenerateInDDL>
</FKIndexAssociation>
