<?xml version = '1.0' encoding = 'UTF-8'?>
<FKIndexAssociation class="oracle.dbtools.crest.model.design.relational.FKIndexAssociation" directorySegmentName="seg_2" id="C8075BDF-288D-D4FF-0D1E-AF525E114C1D" containerWithKeyObject="939B6A6B-CB3E-E184-F1FB-C831EC20C755" localFKIndex="9B910994-4117-6E0F-3F2A-80F14044165B" name="RMPI_R_DF_FK">
<sourceConnName>Oracle-RDS</sourceConnName>
<sourceObjSchema>ADMIN</sourceObjSchema>
<sourceObjName>RMPI_R_DF_FK</sourceObjName>
<createdBy>johan</createdBy>
<createdTime>2023-02-17 08:31:34 UTC</createdTime>
<ownerDesignName>ERD</ownerDesignName>
<referredTableLongName>ADMIN.R_DIGITAL_FORMAT</referredTableLongName>
<deleteRule>NO ACTION</deleteRule>
<referredTableID>0F9E3504-3590-629F-AFDC-49119AADA085</referredTableID>
<keyObject>D49D6331-8E02-5228-109D-6C3C4F0398E8</keyObject>
<referredKeyID>D49D6331-8E02-5228-109D-6C3C4F0398E8</referredKeyID>
<mandatory>false</mandatory>
<refColNames>DIGITAL_FORMAT</refColNames>
<transferable>true</transferable>
<rely>false</rely>
<columnDependencyConstraintGenerateInDDL>true</columnDependencyConstraintGenerateInDDL>
</FKIndexAssociation>
