<?xml version = '1.0' encoding = 'UTF-8'?>
<FKIndexAssociation class="oracle.dbtools.crest.model.design.relational.FKIndexAssociation" directorySegmentName="seg_0" id="9DC117C8-89E6-6A27-DABF-7C2F0B0EAEB9" containerWithKeyObject="94F2D8B6-038F-7587-AA1F-DEE1337C934E" localFKIndex="A9C64D84-663B-DEBF-915C-198DD677724E" name="CSCT_R_CTT_FK">
<sourceConnName>Oracle-RDS</sourceConnName>
<sourceObjSchema>ADMIN</sourceObjSchema>
<sourceObjName>CSCT_R_CTT_FK</sourceObjName>
<createdBy>johan</createdBy>
<createdTime>2023-02-21 03:16:46 UTC</createdTime>
<ownerDesignName>ERD</ownerDesignName>
<importedID>E6AB8204-0109-C945-A25A-57886DF81794</importedID>
<referredTableLongName>ADMIN.R_CS_TRANSFORM_TYPE</referredTableLongName>
<deleteRule>NO ACTION</deleteRule>
<referredTableID>6DBA89E1-8EB7-6730-81A1-4C7A6C26ABF8</referredTableID>
<keyObject>CE993616-27C2-CC80-D5EE-8D50409D23D4</keyObject>
<referredKeyID>CE993616-27C2-CC80-D5EE-8D50409D23D4</referredKeyID>
<mandatory>false</mandatory>
<refColNames>TRANSFORM_TYPE</refColNames>
<transferable>true</transferable>
<rely>false</rely>
<columnDependencyConstraintGenerateInDDL>true</columnDependencyConstraintGenerateInDDL>
</FKIndexAssociation>
