<?xml version = '1.0' encoding = 'UTF-8'?>
<FKIndexAssociation class="oracle.dbtools.crest.model.design.relational.FKIndexAssociation" directorySegmentName="seg_1" id="53B1B533-9AED-6FA3-AE5C-79954D91D8F5" containerWithKeyObject="E0ECD131-9BDE-7C15-1669-E93DAF0BCDFC" localFKIndex="56E00CE2-7B00-9760-021E-A0CCB1B0FA49" name="CSGD_CSE_FK">
<sourceConnName>Oracle-RDS</sourceConnName>
<sourceObjSchema>ADMIN</sourceObjSchema>
<sourceObjName>CSGD_CSE_FK</sourceObjName>
<createdBy>johan</createdBy>
<createdTime>2023-02-20 09:08:05 UTC</createdTime>
<ownerDesignName>ERD</ownerDesignName>
<importedID>8E4FF70B-9364-D032-8C67-EF0AF157C633</importedID>
<referredTableLongName>ADMIN.CS_ELLIPSOID</referredTableLongName>
<deleteRule>NO ACTION</deleteRule>
<referredTableID>7B6FB8D7-BC67-0C0F-007B-A32DD1F8B954</referredTableID>
<keyObject>0293D218-CD26-0898-2AC3-9E2F82457F63</keyObject>
<referredKeyID>0293D218-CD26-0898-2AC3-9E2F82457F63</referredKeyID>
<mandatory>false</mandatory>
<refColNames>ELLIPSOID_ID</refColNames>
<transferable>true</transferable>
<rely>false</rely>
<columnDependencyConstraintGenerateInDDL>true</columnDependencyConstraintGenerateInDDL>
</FKIndexAssociation>
