<?xml version = '1.0' encoding = 'UTF-8'?>
<FKIndexAssociation class="oracle.dbtools.crest.model.design.relational.FKIndexAssociation" directorySegmentName="seg_1" id="6138E164-B9A9-E60E-3E2F-994F5AFFF494" containerWithKeyObject="E0ECD131-9BDE-7C15-1669-E93DAF0BCDFC" localFKIndex="6ABF5050-4880-130F-1FBC-C5FDEF5CA85B" name="CSGD_A_FK">
<sourceConnName>Oracle-RDS</sourceConnName>
<sourceObjSchema>ADMIN</sourceObjSchema>
<sourceObjName>CSGD_A_FK</sourceObjName>
<createdBy>johan</createdBy>
<createdTime>2023-02-20 09:08:05 UTC</createdTime>
<ownerDesignName>ERD</ownerDesignName>
<importedID>954B3454-FC13-4401-B725-98CB81B81ABF</importedID>
<referredTableLongName>ADMIN.AREA</referredTableLongName>
<deleteRule>NO ACTION</deleteRule>
<referredTableID>2A9320A7-DCCA-D17A-DC20-A20DEEE24A32</referredTableID>
<keyObject>BCE75B1B-90D9-2258-A4C4-05A28012CFE3</keyObject>
<referredKeyID>BCE75B1B-90D9-2258-A4C4-05A28012CFE3</referredKeyID>
<mandatory>false</mandatory>
<refColNames>AREA_ID,AREA_TYPE</refColNames>
<transferable>true</transferable>
<rely>false</rely>
<columnDependencyConstraintGenerateInDDL>true</columnDependencyConstraintGenerateInDDL>
</FKIndexAssociation>
