<?xml version = '1.0' encoding = 'UTF-8'?>
<FKIndexAssociation class="oracle.dbtools.crest.model.design.relational.FKIndexAssociation" directorySegmentName="seg_1" id="C2AA769F-10E1-2294-E16B-2457D4E5A051" containerWithKeyObject="3C3DF17E-BB92-5158-49F0-310C58D0A303" localFKIndex="3F5D2084-2827-18DF-B440-983679D85376" name="INS_R_INST_FK">
<sourceConnName>Oracle-RDS</sourceConnName>
<sourceObjSchema>ADMIN</sourceObjSchema>
<sourceObjName>INS_R_INST_FK</sourceObjName>
<createdBy>johan</createdBy>
<createdTime>2023-02-20 09:22:16 UTC</createdTime>
<ownerDesignName>ERD</ownerDesignName>
<importedID>7191D056-BBB5-1EE6-849C-91AD4C114EBD</importedID>
<referredTableLongName>ADMIN.R_INSTRUMENT_TYPE</referredTableLongName>
<deleteRule>NO ACTION</deleteRule>
<referredTableID>9A1B01EC-5824-BDE5-B99F-476946AAD60E</referredTableID>
<keyObject>339AF63D-BFE0-7120-1BA0-089A9316D589</keyObject>
<referredKeyID>339AF63D-BFE0-7120-1BA0-089A9316D589</referredKeyID>
<mandatory>false</mandatory>
<refColNames>LAND_INSTRUMENT_TYPE</refColNames>
<transferable>true</transferable>
<rely>false</rely>
<columnDependencyConstraintGenerateInDDL>true</columnDependencyConstraintGenerateInDDL>
</FKIndexAssociation>
