{"SEIS_LINE": {"Column Name": {"0": "SEIS_SET_SUBTYPE", "1": "SEIS_LINE_ID", "2": "ACTIVE_IND", "3": "DIMENSION", "4": "EFFECTIVE_DATE", "5": "EXPIRY_DATE", "6": "LINE_NAME", "7": "PPDM_GUID", "8": "REFRACTION_REFLECTION", "9": "REMARK", "10": "RESHOOT_OF_SET_ID", "11": "RESHOOT_SEIS_SET_SUBTYPE", "12": "SEIS_ACQTN_SET_SUBTYPE", "13": "SEIS_ACQTN_SURVEY_ID", "14": "SEIS_SPECTRUM_TYPE", "15": "SOURCE", "16": "TEST_EXPERIMENTAL", "17": "ROW_CHANGED_BY", "18": "ROW_CHANGED_DATE", "19": "ROW_CREATED_BY", "20": "ROW_CREATED_DATE", "21": "ROW_EFFECTIVE_DATE", "22": "ROW_EXPIRY_DATE", "23": "ROW_QUALITY"}, "Null": {"0": "N", "1": "N", "2": "Y", "3": "Y", "4": "Y", "5": "Y", "6": "Y", "7": "Y", "8": "Y", "9": "Y", "10": "Y", "11": "Y", "12": "Y", "13": "Y", "14": "Y", "15": "Y", "16": "Y", "17": "Y", "18": "Y", "19": "Y", "20": "Y", "21": "Y", "22": "Y", "23": "Y"}, "Data Type": {"0": "VARCHAR2", "1": "VARCHAR2", "2": "VARCHAR2", "3": "VARCHAR2", "4": "DATE", "5": "DATE", "6": "VARCHAR2", "7": "VARCHAR2", "8": "VARCHAR2", "9": "VARCHAR2", "10": "VARCHAR2", "11": "VARCHAR2", "12": "VARCHAR2", "13": "VARCHAR2", "14": "VARCHAR2", "15": "VARCHAR2", "16": "VARCHAR2", "17": "VARCHAR2", "18": "DATE", "19": "VARCHAR2", "20": "DATE", "21": "DATE", "22": "DATE", "23": "VARCHAR2"}, "Length": {"0": "30", "1": "40", "2": "1", "3": "40", "4": "DATE", "5": "DATE", "6": "255", "7": "38", "8": "40", "9": "2000", "10": "40", "11": "30", "12": "30", "13": "40", "14": "40", "15": "40", "16": "40", "17": "30", "18": "DATE", "19": "30", "20": "DATE", "21": "DATE", "22": "DATE", "23": "40"}, "Key": {"0": "P", "1": "P", "2": NaN, "3": NaN, "4": NaN, "5": NaN, "6": NaN, "7": NaN, "8": NaN, "9": NaN, "10": NaN, "11": NaN, "12": NaN, "13": NaN, "14": NaN, "15": NaN, "16": NaN, "17": NaN, "18": NaN, "19": NaN, "20": NaN, "21": NaN, "22": NaN, "23": NaN}, "Ref Table(s)": {"0": "SEIS_SET", "1": "SEIS_SET", "2": NaN, "3": "R_SEIS_DIMENSION", "4": NaN, "5": NaN, "6": NaN, "7": NaN, "8": NaN, "9": NaN, "10": "SEIS_LINE", "11": "SEIS_LINE", "12": "SEIS_ACQTN_SURVEY", "13": "SEIS_ACQTN_SURVEY", "14": "R_SEIS_SPECTRUM_TYPE", "15": "R_SOURCE", "16": NaN, "17": NaN, "18": NaN, "19": NaN, "20": NaN, "21": NaN, "22": NaN, "23": "R_PPDM_ROW_QUALITY"}, "Column Comment": {"0": "SEISMIC SET SUBTYPE: The seismic set type column is used to enforce a\rrelationship between the SEIS SET supertype and its valid sub types. Values for this\rcolumn must be the name of the table that is the valid sub type for this row of data.\rValidentries include SEIS_LINE, SEIS_SEGMENT, SEIS_SURVEY, SEIS_PLAN,\rSEIS_WELL, SEIS_PROC_SET, SEIS_INTERP_SET or SEIS_3D.", "1": "SEISMIC LINE ID: A unique identifier for a seismic line.", "2": "ACTIVE INDICATOR: A Y/N flag indicating whether this row of data is currently either\ractive / valid (Y) or inactive / invalid (N).", "3": "DIMENSION: The dimension or geometry of the seismic data. May be 1D, 2D, 3D,\rswath, 3D water bottom", "4": "EFFECTIVE DATE: The date that the data in this row first came into effect.", "5": "EXPIRY DATE: The date that the data in this row was no longer active or in effect.", "6": "SEISMIC NAVIGATION NAME: authorized or preferred version of the line name to\rbe used for reporting and mapping.", "7": "ROW_MANAGEMENT_GUID: This value may be used to provide a global unique\ridentifier for this row of data. Use of this column is not mandatory, but if used,\roptional PPDM NOT NULL and UNIQUE INDEX constraints provided in the data\rmodel DDL should be created.", "8": "REFLECTION REFRACTION INDICATOR: Indicates whether the navigation includes\rreflection, refraction or both types of recording.", "9": "REASON: why the seismic navigation was created.", "10": "SEISMIC SET: A seismic set is a super type of various types of seismic collections.", "11": "SEISMIC SET SUBTYPE: The seismic set type column is used to enforce a\rrelationship between the SEIS SET supertype and its valid sub types. Values for this\rcolumn must be the name of the table that is the valid sub type for this row of data.\rValid entries include SEIS_LINE, SEIS_SEGMENT, SEIS_SURVEY, SEIS_PLAN,\rSEIS_WELL, SEIS_PROC_SET, SEIS_INTERP_SET or SEIS_3D.", "12": "SEISMIC SET SUBTYPE: The seismic set type column is used to enforce a\rrelationship between the SEIS SET supertype and its valid sub types. Values for this\rcolumn must be the name of the table that is the valid sub type for this row of\rdata.Valid entries include SEIS_LINE, SEIS_SEGMENT, SEIS_SURVEY,\rSEIS_PLAN, SEIS_WELL, SEIS_PROC_SET, SEIS_INTERP_SET or SEIS_3D.", "13": "SEISMIC ACQUISITION ID: Seismic acquisition set identifier", "14": "SPECTRUM: Indicates additional types of measurements taken. May be magnetic,\relectromagnetic, gravity, shearwave...", "15": "SOURCE: The individual, company, state, or government agency designated as the\rsource of information for this row.", "16": "TEST OR EXPERIMENTAL: indicates whether the seismic was test or experimental.", "17": "ROW CHANGED BY: Application login id of the user who last changed the row.", "18": "ROW CHANGED DATE: System date of the last time the row was changed.", "19": "ROW CREATED BY: System user who created this row of data.", "20": "ROW CREATED DATE: Date that the row was created on.", "21": "ROW_EFFECTIVE_DATE: A system assigned date that specified when a row of data\ris effective from a systems perspective. This may be the date that a row of data was\rmade available to end users, for example.", "22": "ROW_EXPIRY_DATE: A system assigned date that specified when a row of data is\rno longer effective from a systems perspective. This may be the date that a row of\rdata was no longer available to end users, for example.", "23": "PPDM ROW QUALITY: A set of values indicating the quality of data in this row,\rusually with reference to the method or procedures used to load the data, although\rother types of quality reference are permitted."}}}