{"WELL_AIR_DRILL_INTERVAL": {"Column Name": {"0": "UWI", "1": "AIR_DRILL_SOURCE", "2": "AIR_DRILL_OBS_NO", "3": "DEPTH_OBS_NO", "4": "ACTIVE_IND", "5": "AIR_GAS_CODE", "6": "BASE_DEPTH", "7": "BASE_DEPTH_OUOM", "8": "COMPRESSOR_RATE_VOLUME", "9": "COMPRESSOR_RATE_VOLUME", "10": "EFFECTIVE_DATE", "11": "EXPIRY_DATE", "12": "MAX_INTERVAL_PRESSURE", "13": "MAX_INTERVAL_PRESSURE_O", "14": "PPDM_GUID", "15": "REMARK", "16": "SOURCE", "17": "TOP_DEPTH", "18": "TOP_DEPTH_OUOM", "19": "WATER_INFLUX_AMOUNT", "20": "WATER_INFLUX_AMOUNT_OUO", "21": "ROW_CHANGED_BY", "22": "ROW_CHANGED_DATE", "23": "ROW_CREATED_BY", "24": "ROW_CREATED_DATE", "25": "ROW_EFFECTIVE_DATE", "26": "ROW_EXPIRY_DATE", "27": "ROW_QUALITY"}, "Null": {"0": "N", "1": "N", "2": "N", "3": "N", "4": "Y", "5": "Y", "6": "Y", "7": "Y", "8": "Y", "9": "OUYOM", "10": "Y", "11": "Y", "12": "Y", "13": "OMY", "14": "Y", "15": "Y", "16": "Y", "17": "Y", "18": "Y", "19": "Y", "20": "Y", "21": "Y", "22": "Y", "23": "Y", "24": "Y", "25": "Y", "26": "Y", "27": "Y"}, "Data Type": {"0": "VARCHAR2", "1": "VARCHAR2", "2": "NUMBER", "3": "NUMBER", "4": "VARCHAR2", "5": "VARCHAR2", "6": "NUMBER", "7": "VARCHAR2", "8": "NUMBER", "9": "VARCHAR2", "10": "DATE", "11": "DATE", "12": "NUMBER", "13": "VARCHAR2", "14": "VARCHAR2", "15": "VARCHAR2", "16": "VARCHAR2", "17": "NUMBER", "18": "VARCHAR2", "19": "NUMBER", "20": "VARCHAR2", "21": "VARCHAR2", "22": "DATE", "23": "VARCHAR2", "24": "DATE", "25": "DATE", "26": "DATE", "27": "VARCHAR2"}, "Length": {"0": "40", "1": "40", "2": "8", "3": "8", "4": "1", "5": "40", "6": "15,5", "7": "40", "8": "14,4", "9": "40", "10": "DATE", "11": "DATE", "12": "8,2", "13": "40", "14": "38", "15": "2000", "16": "40", "17": "15,5", "18": "40", "19": "10,5", "20": "40", "21": "30", "22": "DATE", "23": "30", "24": "DATE", "25": "DATE", "26": "DATE", "27": "40"}, "Key": {"0": "P", "1": "P", "2": "P", "3": "P", "4": NaN, "5": NaN, "6": NaN, "7": NaN, "8": NaN, "9": NaN, "10": NaN, "11": NaN, "12": NaN, "13": NaN, "14": NaN, "15": NaN, "16": NaN, "17": NaN, "18": NaN, "19": NaN, "20": NaN, "21": NaN, "22": NaN, "23": NaN, "24": NaN, "25": NaN, "26": NaN, "27": NaN}, "Ref Table(s)": {"0": "WELL_AIR_DRILL", "1": "WELL_AIR_DRILL", "2": "WELL_AIR_DRILL", "3": NaN, "4": NaN, "5": "R_AIR_GAS_CODE", "6": NaN, "7": "PPDM_UNIT_OF_MEASURE", "8": NaN, "9": "PPDM_UNIT_OF_MEASURE", "10": NaN, "11": NaN, "12": NaN, "13": "PPDM_UNIT_OF_MEASURE", "14": NaN, "15": NaN, "16": "R_SOURCE", "17": NaN, "18": "PPDM_UNIT_OF_MEASURE", "19": NaN, "20": "PPDM_UNIT_OF_MEASURE", "21": NaN, "22": NaN, "23": NaN, "24": NaN, "25": NaN, "26": NaN, "27": "R_PPDM_ROW_QUALITY"}, "Column Comment": {"0": "UNIQUE WELL IDENTIFIER: A unique name, code or number designated as the\rprimary key for this row.", "1": "SOURCE: The individual, company, state, or government agency designated as the\rsource of information for this row.", "2": "AIR DRLLING OBSERVATION NUMBER: The air drilling observation number used\rfor the air drilling contractor record.", "3": "DEPTH OBSERVATOIN NUMBER: identifies the depth interval.", "4": "ACTIVE INDICATOR: A Y/N flag indicating whether this row of data is currently either\ractive / valid (Y) or inactive / invalid (N).", "5": "AIR GAS CODE: The type of fluid supplied by the drilling compressor. For example,\rthe fluid can be Air or Gas.", "6": "BASE DEPTH: Measured depth from the surface to the bottom of the interval drilled\rwith compressed air/gas.", "7": "BASE DEPTH OUOM: Base depth original unit of measure.", "8": "COMPRESSOR RATE VOLUME: Value for the rate of air/gas delivered by the air\rcompressor while drilling the interval. The rate is usually expressed in cubic feet per\rminute.", "9": "COMPRESSOR RATE VOLUME OUOM: Air/gas volume rate original unit of\rmeasure.", "10": "EFFECTIVE DATE: The date that the data in this row first came into effect.", "11": "EXPIRY DATE: The date that the data in this row was no longer active or in effect.", "12": "MAXIMUM INTERVAL PRESSURE: Value for the maximum gauge pressure\rrecorded during air drilling of the interval.", "13": "MAXIMUM INTERVAL PRESSURE OUOM: Maximum gauge pressure original unit of\rmeasure.", "14": "ROW_MANAGEMENT_GUID: This value may be used to provide a global unique\ridentifier for this row of data. Use of this column is not mandatory, but if used,\roptional PPDM NOT NULL and UNIQUE INDEX constraints provided in the data\rmodel DDL shouldbe created.", "15": "REMARK: Narrative remarks about this row of data.", "16": "SOURCE: The individual, company, state, or government agency designated as the\rsource of information for this row.", "17": "TOP DEPTH: Measured depth from the surface to the top of the interval drilled with\rcompressed air/gas.", "18": "TOP DEPTH OUOM: Top depth original unit of measure.", "19": "WATER INFLUX AMOUNT: Value for the amount of water entering the wellbore\rduring the air/gas drilling.", "20": "WATER INFLUX AMOUNT OUOM: Water influx original unit of measure.", "21": "ROW CHANGED BY: Application login id of the user who last changed the row.", "22": "ROW CHANGED DATE: System date of the last time the row was changed.", "23": "ROW CREATED BY: System user who created this row of data.", "24": "ROW CREATED DATE: Date that the row was created on.", "25": "ROW_EFFECTIVE_DATE: A system assigned date that specified when a row of data\ris effective from a systems perspective. This may be the date that a row of data was\rmade available to end users, for example.", "26": "ROW_EXPIRY_DATE: A system assigned date that specified when a row of data is\rno longer effective from a systems perspective. This may be the date that a row of\rdata was no longer available to end users, for example.", "27": "PPDM ROW QUALITY: A set of values indicating the quality of data in this row,\rusually with reference to the method or procedures used to load the data, although\rother types of quality reference are permitted."}}}