<?xml version = '1.0' encoding = 'UTF-8'?>
<TableProxyOraclev12c class="oracle.dbtools.crest.model.design.storage.oracle.v12c.TableProxyOraclev12c" name="R_SEIS_STATION_TYPE" directorySegmentName="seg_1" id="B9942F72-6C1E-BFC0-FAF4-9ED4FE35C1D8">
<createdBy>johan</createdBy>
<createdTime>2023-02-21 08:53:40 UTC</createdTime>
<ownerDesignName>ERD</ownerDesignName>
<schemaObject>C44CCA9D-1F95-DF2E-53BC-549A9870B1AD</schemaObject>
<logging>YES</logging>
<partitionedRowMovement>DISABLE</partitionedRowMovement>
<segment>639A7E5F-6B67-E39C-B244-6C748E55E645</segment>
<tableSpace>43F277F0-BD05-5BB7-C2F2-AD4D531E6BD8</tableSpace>
<temporaryChanged>false</temporaryChanged>
<accessDriverType>oracle_loader</accessDriverType>
<rejectLimit></rejectLimit>
<inMemory>NO</inMemory>
<columnProxies itemClass="oracle.dbtools.crest.model.design.storage.oracle.v12c.ColumnProxyOraclev12c">
<ColumnProxy name="REMARK" id="18AEF0D7-EA4C-996F-03A2-38040CFB46B6">
<createdBy>johan</createdBy>
<createdTime>2023-02-21 08:53:40 UTC</createdTime>
<ownerDesignName>ERD</ownerDesignName>
</ColumnProxy>
<ColumnProxy name="ROW_CREATED_BY" id="1B145CDF-1BB5-225E-8A36-B302470A1E3D">
<createdBy>johan</createdBy>
<createdTime>2023-02-21 08:53:40 UTC</createdTime>
<ownerDesignName>ERD</ownerDesignName>
</ColumnProxy>
<ColumnProxy name="SHORT_NAME" id="1B819D60-68CC-2A6E-91F4-C1B804E843B4">
<createdBy>johan</createdBy>
<createdTime>2023-02-21 08:53:40 UTC</createdTime>
<ownerDesignName>ERD</ownerDesignName>
</ColumnProxy>
<ColumnProxy name="PPDM_GUID" id="2068120D-A890-5E58-E247-6AC7E67B8498">
<createdBy>johan</createdBy>
<createdTime>2023-02-21 08:53:40 UTC</createdTime>
<ownerDesignName>ERD</ownerDesignName>
</ColumnProxy>
<ColumnProxy name="ROW_CREATED_DATE" id="32E60241-E7F0-5BC3-2AEC-23133E94D922">
<createdBy>johan</createdBy>
<createdTime>2023-02-21 08:53:40 UTC</createdTime>
<ownerDesignName>ERD</ownerDesignName>
</ColumnProxy>
<ColumnProxy name="ROW_EFFECTIVE_DATE" id="3A5F49E0-02F8-5FB6-A031-3ECA3B754BA9">
<createdBy>johan</createdBy>
<createdTime>2023-02-21 08:53:40 UTC</createdTime>
<ownerDesignName>ERD</ownerDesignName>
</ColumnProxy>
<ColumnProxy name="ABBREVIATION" id="438FAF5F-C0EC-05C2-96C8-99B527975DE7">
<createdBy>johan</createdBy>
<createdTime>2023-02-21 08:53:40 UTC</createdTime>
<ownerDesignName>ERD</ownerDesignName>
</ColumnProxy>
<ColumnProxy name="ROW_CHANGED_DATE" id="551E71CD-D3B7-7B48-4D88-AFAB16044624">
<createdBy>johan</createdBy>
<createdTime>2023-02-21 08:53:40 UTC</createdTime>
<ownerDesignName>ERD</ownerDesignName>
</ColumnProxy>
<ColumnProxy name="LONG_NAME" id="5D24DA31-D641-5639-F29C-CBA2910941E5">
<createdBy>johan</createdBy>
<createdTime>2023-02-21 08:53:40 UTC</createdTime>
<ownerDesignName>ERD</ownerDesignName>
</ColumnProxy>
<ColumnProxy name="EFFECTIVE_DATE" id="82256934-2FC6-04EF-EB2F-62AA1933B6AB">
<createdBy>johan</createdBy>
<createdTime>2023-02-21 08:53:40 UTC</createdTime>
<ownerDesignName>ERD</ownerDesignName>
</ColumnProxy>
<ColumnProxy name="EXPIRY_DATE" id="93D5BC57-E98B-5AF8-318F-28F1BB00C05C">
<createdBy>johan</createdBy>
<createdTime>2023-02-21 08:53:40 UTC</createdTime>
<ownerDesignName>ERD</ownerDesignName>
</ColumnProxy>
<ColumnProxy name="SEIS_STATION_TYPE" id="B7E98739-7F98-302F-AC76-04E882035E84">
<createdBy>johan</createdBy>
<createdTime>2023-02-21 08:53:40 UTC</createdTime>
<ownerDesignName>ERD</ownerDesignName>
</ColumnProxy>
<ColumnProxy name="SOURCE" id="C96BB551-A77B-A279-C996-8DE0B0CDD4D5">
<createdBy>johan</createdBy>
<createdTime>2023-02-21 08:53:40 UTC</createdTime>
<ownerDesignName>ERD</ownerDesignName>
</ColumnProxy>
<ColumnProxy name="ROW_EXPIRY_DATE" id="CB5F9AD9-390A-1501-7730-F5F058D9401C">
<createdBy>johan</createdBy>
<createdTime>2023-02-21 08:53:40 UTC</createdTime>
<ownerDesignName>ERD</ownerDesignName>
</ColumnProxy>
<ColumnProxy name="ROW_QUALITY" id="E54A66A0-AAC6-B1D8-DAD5-10FB964F4573">
<createdBy>johan</createdBy>
<createdTime>2023-02-21 08:53:40 UTC</createdTime>
<ownerDesignName>ERD</ownerDesignName>
</ColumnProxy>
<ColumnProxy name="ACTIVE_IND" id="E95285E2-12AB-3384-2484-2357B8201732">
<createdBy>johan</createdBy>
<createdTime>2023-02-21 08:53:40 UTC</createdTime>
<ownerDesignName>ERD</ownerDesignName>
</ColumnProxy>
<ColumnProxy name="ROW_CHANGED_BY" id="F2A925C1-56D6-C051-AF48-E1E0057ACD71">
<createdBy>johan</createdBy>
<createdTime>2023-02-21 08:53:40 UTC</createdTime>
<ownerDesignName>ERD</ownerDesignName>
</ColumnProxy>
</columnProxies>
<indexProxies>
<IndexProxy class="oracle.dbtools.crest.model.design.storage.oracle.v10g.IndexProxyOraclev10g" name="R_SST2_GUID" id="61245673-5D36-EF46-01DB-D21C55B9343B">
<createdBy>johan</createdBy>
<createdTime>2023-02-21 08:53:40 UTC</createdTime>
<ownerDesignName>ERD</ownerDesignName>
<schemaObject>C44CCA9D-1F95-DF2E-53BC-549A9870B1AD</schemaObject>
<segment>59752463-067A-2B05-23C9-4945E932943D</segment>
<tableSpace>43F277F0-BD05-5BB7-C2F2-AD4D531E6BD8</tableSpace>
</IndexProxy>
<IndexProxy class="oracle.dbtools.crest.model.design.storage.oracle.v10g.IndexProxyOraclev10g" name="R_SST2_PK" id="A03504CE-5F24-A686-5BAE-84B915EC0E2E">
<createdBy>johan</createdBy>
<createdTime>2023-02-21 08:53:40 UTC</createdTime>
<ownerDesignName>ERD</ownerDesignName>
<schemaObject>C44CCA9D-1F95-DF2E-53BC-549A9870B1AD</schemaObject>
<segment>59752463-067A-2B05-23C9-4945E932943D</segment>
<tableSpace>43F277F0-BD05-5BB7-C2F2-AD4D531E6BD8</tableSpace>
</IndexProxy>
</indexProxies>
<foreignKeys>
<ForeignKey class="oracle.dbtools.crest.model.design.storage.oracle.v10g.FKProxyOraclev10g" name="R_SST2_R_S_FK" id="64567C15-958A-22E3-DA95-1A6495E22589">
<createdBy>johan</createdBy>
<createdTime>2023-02-21 08:53:40 UTC</createdTime>
<ownerDesignName>ERD</ownerDesignName>
</ForeignKey>
<ForeignKey class="oracle.dbtools.crest.model.design.storage.oracle.v10g.FKProxyOraclev10g" name="R_SST2_R_PRQ_FK" id="E7E500B4-2180-1569-C31B-A9352F7971A9">
<createdBy>johan</createdBy>
<createdTime>2023-02-21 08:53:40 UTC</createdTime>
<ownerDesignName>ERD</ownerDesignName>
</ForeignKey>
</foreignKeys>
<primaryKeys>
<PrimaryKey class="oracle.dbtools.crest.model.design.storage.oracle.v10g.PKProxyOraclev10g" name="R_SST2_PK" id="4C083508-4952-E39A-D225-A927349402A7">
<createdBy>johan</createdBy>
<createdTime>2023-02-21 08:53:40 UTC</createdTime>
<ownerDesignName>ERD</ownerDesignName>
<segment>59752463-067A-2B05-23C9-4945E932943D</segment>
<tableSpace>43F277F0-BD05-5BB7-C2F2-AD4D531E6BD8</tableSpace>
<existingIndex>A03504CE-5F24-A686-5BAE-84B915EC0E2E</existingIndex>
<indexSegment>59752463-067A-2B05-23C9-4945E932943D</indexSegment>
<indexSort>SORTED</indexSort>
<usingIndex>BY INDEX NAME</usingIndex>
</PrimaryKey>
</primaryKeys>
<uniqueKeys>
<UniqueKey class="oracle.dbtools.crest.model.design.storage.oracle.v10g.UniqueOraclev10g" name="R_SST2_GUID" id="DCF4EE2E-0EE9-FDFE-6C16-F58AE01297EE">
<createdBy>johan</createdBy>
<createdTime>2023-02-21 08:53:40 UTC</createdTime>
<ownerDesignName>ERD</ownerDesignName>
<segment>59752463-067A-2B05-23C9-4945E932943D</segment>
<tableSpace>43F277F0-BD05-5BB7-C2F2-AD4D531E6BD8</tableSpace>
<existingIndex>61245673-5D36-EF46-01DB-D21C55B9343B</existingIndex>
<indexSegment>59752463-067A-2B05-23C9-4945E932943D</indexSegment>
<indexSort>SORTED</indexSort>
<usingIndex>BY INDEX NAME</usingIndex>
</UniqueKey>
</uniqueKeys>
</TableProxyOraclev12c>
