<?xml version = '1.0' encoding = 'UTF-8'?>
<FKIndexAssociation class="oracle.dbtools.crest.model.design.relational.FKIndexAssociation" directorySegmentName="seg_6" id="2529793C-C858-A22A-22B5-2A2A08B4CB7E" containerWithKeyObject="5588BD20-93B6-F10D-F7EB-C78B221A31F4" localFKIndex="CF6313AE-C286-D7D0-80DD-29E0E52868BA" name="R_RP1_R_PRQ_FK">
<sourceConnName>Oracle-RDS</sourceConnName>
<sourceObjSchema>ADMIN</sourceObjSchema>
<sourceObjName>R_RP1_R_PRQ_FK</sourceObjName>
<createdBy>johan</createdBy>
<createdTime>2023-02-20 09:26:50 UTC</createdTime>
<ownerDesignName>ERD</ownerDesignName>
<importedID>F26B91DA-8171-59F4-4E9D-F51B7C3C96D0</importedID>
<referredTableLongName>ADMIN.R_PPDM_ROW_QUALITY</referredTableLongName>
<deleteRule>NO ACTION</deleteRule>
<referredTableID>B69D3897-34A3-C6E6-E606-79822E492C0C</referredTableID>
<keyObject>7A1934D0-1FE1-434F-8B49-B711D064D06D</keyObject>
<referredKeyID>7A1934D0-1FE1-434F-8B49-B711D064D06D</referredKeyID>
<mandatory>false</mandatory>
<refColNames>ROW_QUALITY_ID</refColNames>
<transferable>true</transferable>
<rely>false</rely>
<columnDependencyConstraintGenerateInDDL>true</columnDependencyConstraintGenerateInDDL>
</FKIndexAssociation>
