<?xml version = '1.0' encoding = 'UTF-8'?>
<FKIndexAssociation class="oracle.dbtools.crest.model.design.relational.FKIndexAssociation" directorySegmentName="seg_6" id="3A204071-598B-75DB-AFD7-132FCFCAC909" containerWithKeyObject="7F6F7BA5-24B1-3C37-A0FC-3EA1154B8D5F" localFKIndex="A19801D7-22F2-E0FE-0A00-54EA98141D07" name="R_PS1_PSWA_FK">
<sourceConnName>Oracle-RDS</sourceConnName>
<sourceObjSchema>ADMIN</sourceObjSchema>
<sourceObjName>R_PS1_PSWA_FK</sourceObjName>
<createdBy>johan</createdBy>
<createdTime>2023-02-20 09:18:48 UTC</createdTime>
<ownerDesignName>ERD</ownerDesignName>
<importedID>FCFF44B1-4364-A3FC-E2E4-F3942AC8D3C8</importedID>
<referredTableLongName>ADMIN.PPDM_SW_APPLICATION</referredTableLongName>
<deleteRule>NO ACTION</deleteRule>
<referredTableID>DE8DAAC6-88C5-0DB8-3B70-7DC7DCB1F9C4</referredTableID>
<keyObject>0A1D3FCC-EBA7-D92A-BBFE-746C3217B7F6</keyObject>
<referredKeyID>0A1D3FCC-EBA7-D92A-BBFE-746C3217B7F6</referredKeyID>
<mandatory>false</mandatory>
<refColNames>SW_APPLICATION_ID</refColNames>
<transferable>true</transferable>
<rely>false</rely>
<columnDependencyConstraintGenerateInDDL>true</columnDependencyConstraintGenerateInDDL>
</FKIndexAssociation>
