<?xml version = '1.0' encoding = 'UTF-8'?>
<TableProxyOraclev12c class="oracle.dbtools.crest.model.design.storage.oracle.v12c.TableProxyOraclev12c" name="ANL_ANALYSIS_STEP" directorySegmentName="seg_1" id="5E15022E-6C1F-8B69-93FA-EF28B543F1A6">
<createdBy>johan</createdBy>
<createdTime>2023-02-21 09:17:52 UTC</createdTime>
<ownerDesignName>ERD</ownerDesignName>
<schemaObject>D9400E64-AD1A-8DFA-B7CC-565DC50367B8</schemaObject>
<logging>YES</logging>
<partitionedRowMovement>DISABLE</partitionedRowMovement>
<segment>0A519A3F-07E4-1D22-5BCF-6389D06B1A3E</segment>
<tableSpace>F77AAD8B-698F-5207-6B5F-A30E25666E1A</tableSpace>
<temporaryChanged>false</temporaryChanged>
<accessDriverType>oracle_loader</accessDriverType>
<rejectLimit></rejectLimit>
<inMemory>NO</inMemory>
<columnProxies itemClass="oracle.dbtools.crest.model.design.storage.oracle.v12c.ColumnProxyOraclev12c">
<ColumnProxy name="STEP_SEQ_NO" id="038BF562-4776-C1DB-B0AE-64A498D1B3FE">
<createdBy>johan</createdBy>
<createdTime>2023-02-21 09:17:52 UTC</createdTime>
<ownerDesignName>ERD</ownerDesignName>
</ColumnProxy>
<ColumnProxy name="ROW_CREATED_BY" id="07F3D823-3EE9-0DF0-A21C-5A5161D7042C">
<createdBy>johan</createdBy>
<createdTime>2023-02-21 09:17:52 UTC</createdTime>
<ownerDesignName>ERD</ownerDesignName>
</ColumnProxy>
<ColumnProxy name="ROW_CHANGED_DATE" id="0E805DFD-A1F7-2CA8-8B04-6BFB40655E74">
<createdBy>johan</createdBy>
<createdTime>2023-02-21 09:17:52 UTC</createdTime>
<ownerDesignName>ERD</ownerDesignName>
</ColumnProxy>
<ColumnProxy name="SAMPLE_FRACTION_TYPE" id="0E9BF613-CE8F-F1CE-F29F-A374D136DF1F">
<createdBy>johan</createdBy>
<createdTime>2023-02-21 09:17:52 UTC</createdTime>
<ownerDesignName>ERD</ownerDesignName>
</ColumnProxy>
<ColumnProxy name="EXPIRY_DATE" id="0F811E2F-1408-2196-6171-29F4E7A21FC7">
<createdBy>johan</createdBy>
<createdTime>2023-02-21 09:17:52 UTC</createdTime>
<ownerDesignName>ERD</ownerDesignName>
</ColumnProxy>
<ColumnProxy name="STEP_COMPLETED_IND" id="17F21953-9966-D69C-A062-37D8E62FEB9D">
<createdBy>johan</createdBy>
<createdTime>2023-02-21 09:17:52 UTC</createdTime>
<ownerDesignName>ERD</ownerDesignName>
</ColumnProxy>
<ColumnProxy name="FINAL_VOLUME" id="182516A6-AA42-998B-3C0E-7C5D5FDDD325">
<createdBy>johan</createdBy>
<createdTime>2023-02-21 09:17:52 UTC</createdTime>
<ownerDesignName>ERD</ownerDesignName>
</ColumnProxy>
<ColumnProxy name="PROBLEM_IND" id="198475EA-45F7-AAA4-3C39-59E7C2E906F9">
<createdBy>johan</createdBy>
<createdTime>2023-02-21 09:17:52 UTC</createdTime>
<ownerDesignName>ERD</ownerDesignName>
</ColumnProxy>
<ColumnProxy name="ROW_EXPIRY_DATE" id="19992CD7-67D7-6BCD-48EC-BDE248476AA9">
<createdBy>johan</createdBy>
<createdTime>2023-02-21 09:17:52 UTC</createdTime>
<ownerDesignName>ERD</ownerDesignName>
</ColumnProxy>
<ColumnProxy name="COMPLETE_DATE" id="252E04FF-0874-4238-7241-AD1195C83A5B">
<createdBy>johan</createdBy>
<createdTime>2023-02-21 09:17:52 UTC</createdTime>
<ownerDesignName>ERD</ownerDesignName>
</ColumnProxy>
<ColumnProxy name="ANL_SOURCE" id="2631A037-996F-F190-75C5-33E3391F235E">
<createdBy>johan</createdBy>
<createdTime>2023-02-21 09:17:52 UTC</createdTime>
<ownerDesignName>ERD</ownerDesignName>
</ColumnProxy>
<ColumnProxy name="ROW_QUALITY" id="2CD89405-E754-80D5-20EE-CD8BC2E248AF">
<createdBy>johan</createdBy>
<createdTime>2023-02-21 09:17:52 UTC</createdTime>
<ownerDesignName>ERD</ownerDesignName>
</ColumnProxy>
<ColumnProxy name="SAMPLE_QUALITY_DESC" id="2E023FCD-08A4-5D5E-34E1-2DAA8B5F485E">
<createdBy>johan</createdBy>
<createdTime>2023-02-21 09:17:52 UTC</createdTime>
<ownerDesignName>ERD</ownerDesignName>
</ColumnProxy>
<ColumnProxy name="EFFECTIVE_DATE" id="391D7A19-C8E0-1872-F3BA-EC38F4ADD710">
<createdBy>johan</createdBy>
<createdTime>2023-02-21 09:17:52 UTC</createdTime>
<ownerDesignName>ERD</ownerDesignName>
</ColumnProxy>
<ColumnProxy name="RECEIVED_DATE" id="3D0CA4EE-C911-BB4D-6814-041FA62F3F63">
<createdBy>johan</createdBy>
<createdTime>2023-02-21 09:17:52 UTC</createdTime>
<ownerDesignName>ERD</ownerDesignName>
</ColumnProxy>
<ColumnProxy name="SAMPLE_QUALITY" id="42B1D7C6-17C1-F5AE-3A60-4B168D4CC0E4">
<createdBy>johan</createdBy>
<createdTime>2023-02-21 09:17:52 UTC</createdTime>
<ownerDesignName>ERD</ownerDesignName>
</ColumnProxy>
<ColumnProxy name="METHOD_SET_ID" id="4705FF05-43D4-D48E-4058-B5E6C1AB1AD5">
<createdBy>johan</createdBy>
<createdTime>2023-02-21 09:17:52 UTC</createdTime>
<ownerDesignName>ERD</ownerDesignName>
</ColumnProxy>
<ColumnProxy name="STEP_DESC" id="4BF27614-9DEB-F103-CC93-E32A1EB08979">
<createdBy>johan</createdBy>
<createdTime>2023-02-21 09:17:52 UTC</createdTime>
<ownerDesignName>ERD</ownerDesignName>
</ColumnProxy>
<ColumnProxy name="ANL_DATE" id="5FD6F42C-F533-DAD1-BEF1-FE6387DAF2DA">
<createdBy>johan</createdBy>
<createdTime>2023-02-21 09:17:52 UTC</createdTime>
<ownerDesignName>ERD</ownerDesignName>
</ColumnProxy>
<ColumnProxy name="ANALYSIS_PHASE" id="6DB5B742-FE06-E9A2-9D79-15D7AD672AB4">
<createdBy>johan</createdBy>
<createdTime>2023-02-21 09:17:52 UTC</createdTime>
<ownerDesignName>ERD</ownerDesignName>
</ColumnProxy>
<ColumnProxy name="FINAL_WEIGHT" id="7479FB2C-4D39-2187-849F-260A4B39A76C">
<createdBy>johan</createdBy>
<createdTime>2023-02-21 09:17:52 UTC</createdTime>
<ownerDesignName>ERD</ownerDesignName>
</ColumnProxy>
<ColumnProxy name="ROW_CREATED_DATE" id="762E1E9C-316D-5861-A0E2-7CEDE9ADD700">
<createdBy>johan</createdBy>
<createdTime>2023-02-21 09:17:52 UTC</createdTime>
<ownerDesignName>ERD</ownerDesignName>
</ColumnProxy>
<ColumnProxy name="REPORTED_DATE" id="7BC39DEE-45B1-9920-B4BF-CFB5C6B7173E">
<createdBy>johan</createdBy>
<createdTime>2023-02-21 09:17:52 UTC</createdTime>
<ownerDesignName>ERD</ownerDesignName>
</ColumnProxy>
<ColumnProxy name="ROW_EFFECTIVE_DATE" id="7E84CEF0-6B3C-6F2D-5509-64C278021DA0">
<createdBy>johan</createdBy>
<createdTime>2023-02-21 09:17:52 UTC</createdTime>
<ownerDesignName>ERD</ownerDesignName>
</ColumnProxy>
<ColumnProxy name="ANALYSIS_ID" id="8752889D-6D47-3250-2721-1794524ABD85">
<createdBy>johan</createdBy>
<createdTime>2023-02-21 09:17:52 UTC</createdTime>
<ownerDesignName>ERD</ownerDesignName>
</ColumnProxy>
<ColumnProxy name="SOURCE" id="8C61957B-D07C-BD7D-C79E-1684074C8821">
<createdBy>johan</createdBy>
<createdTime>2023-02-21 09:17:52 UTC</createdTime>
<ownerDesignName>ERD</ownerDesignName>
</ColumnProxy>
<ColumnProxy name="STEP_REQUESTED_IND" id="961CE53A-25D4-88E1-609E-313F1356F66A">
<createdBy>johan</createdBy>
<createdTime>2023-02-21 09:17:52 UTC</createdTime>
<ownerDesignName>ERD</ownerDesignName>
</ColumnProxy>
<ColumnProxy name="RESULTS_RECEIVED_IND" id="9DCFB679-B629-78CB-BFFA-D22BE6151981">
<createdBy>johan</createdBy>
<createdTime>2023-02-21 09:17:52 UTC</createdTime>
<ownerDesignName>ERD</ownerDesignName>
</ColumnProxy>
<ColumnProxy name="END_DATE" id="A40A915E-EFF8-7B91-26EE-3B096AD5BD8C">
<createdBy>johan</createdBy>
<createdTime>2023-02-21 09:17:52 UTC</createdTime>
<ownerDesignName>ERD</ownerDesignName>
</ColumnProxy>
<ColumnProxy name="REMARK" id="A88BA045-AAFE-454F-0601-B364BE4271E1">
<createdBy>johan</createdBy>
<createdTime>2023-02-21 09:17:52 UTC</createdTime>
<ownerDesignName>ERD</ownerDesignName>
</ColumnProxy>
<ColumnProxy name="START_DATE" id="B9C7D1BD-C78F-5B02-A644-8D68B5EB0131">
<createdBy>johan</createdBy>
<createdTime>2023-02-21 09:17:52 UTC</createdTime>
<ownerDesignName>ERD</ownerDesignName>
</ColumnProxy>
<ColumnProxy name="RESULTS_RECEIVED_DATE" id="C1F40C1C-5A7A-6826-A133-FA4417AD029A">
<createdBy>johan</createdBy>
<createdTime>2023-02-21 09:17:52 UTC</createdTime>
<ownerDesignName>ERD</ownerDesignName>
</ColumnProxy>
<ColumnProxy name="PPDM_GUID" id="C6B5B753-A1DE-DFCB-EE7A-B9ACDEC0C644">
<createdBy>johan</createdBy>
<createdTime>2023-02-21 09:17:52 UTC</createdTime>
<ownerDesignName>ERD</ownerDesignName>
</ColumnProxy>
<ColumnProxy name="FINAL_WEIGHT_OUOM" id="C8787753-BBDD-EB66-0763-1436238B81FA">
<createdBy>johan</createdBy>
<createdTime>2023-02-21 09:17:52 UTC</createdTime>
<ownerDesignName>ERD</ownerDesignName>
</ColumnProxy>
<ColumnProxy name="RECOVERED_PERCENT" id="CB265E67-7FEB-9664-9C5E-5E92424805D4">
<createdBy>johan</createdBy>
<createdTime>2023-02-21 09:17:52 UTC</createdTime>
<ownerDesignName>ERD</ownerDesignName>
</ColumnProxy>
<ColumnProxy name="STEP_QUALITY_DESC" id="D1A7F229-D1F5-369D-885F-8AF261EF5E24">
<createdBy>johan</createdBy>
<createdTime>2023-02-21 09:17:52 UTC</createdTime>
<ownerDesignName>ERD</ownerDesignName>
</ColumnProxy>
<ColumnProxy name="ACTIVE_IND" id="E4FFAC97-045E-0A18-7809-0D621F5E21CF">
<createdBy>johan</createdBy>
<createdTime>2023-02-21 09:17:52 UTC</createdTime>
<ownerDesignName>ERD</ownerDesignName>
</ColumnProxy>
<ColumnProxy name="METHOD_ID" id="E60B6528-0504-8560-8511-E5970D48CF88">
<createdBy>johan</createdBy>
<createdTime>2023-02-21 09:17:52 UTC</createdTime>
<ownerDesignName>ERD</ownerDesignName>
</ColumnProxy>
<ColumnProxy name="FINAL_VOLUME_OUOM" id="EB18FC4B-3625-583E-A66F-D1AD8DF50418">
<createdBy>johan</createdBy>
<createdTime>2023-02-21 09:17:52 UTC</createdTime>
<ownerDesignName>ERD</ownerDesignName>
</ColumnProxy>
<ColumnProxy name="STEP_QUALITY_TYPE" id="EBE36BC7-F11B-1956-F7CF-84A7E658EBE7">
<createdBy>johan</createdBy>
<createdTime>2023-02-21 09:17:52 UTC</createdTime>
<ownerDesignName>ERD</ownerDesignName>
</ColumnProxy>
<ColumnProxy name="FINAL_VOLUME_PERCENT" id="ECB6101E-16BD-2592-4FCC-95313FB2D72A">
<createdBy>johan</createdBy>
<createdTime>2023-02-21 09:17:52 UTC</createdTime>
<ownerDesignName>ERD</ownerDesignName>
</ColumnProxy>
<ColumnProxy name="ROW_CHANGED_BY" id="FE346F36-6024-23C2-62AC-1B1D0785D896">
<createdBy>johan</createdBy>
<createdTime>2023-02-21 09:17:52 UTC</createdTime>
<ownerDesignName>ERD</ownerDesignName>
</ColumnProxy>
</columnProxies>
<indexProxies>
<IndexProxy class="oracle.dbtools.crest.model.design.storage.oracle.v10g.IndexProxyOraclev10g" name="ANLAS_GUID" id="96D79C01-F913-AF6B-2ABD-7C2DC176B54E">
<createdBy>johan</createdBy>
<createdTime>2023-02-21 09:17:52 UTC</createdTime>
<ownerDesignName>ERD</ownerDesignName>
<schemaObject>D9400E64-AD1A-8DFA-B7CC-565DC50367B8</schemaObject>
<segment>A5F15058-DD63-F951-4B2D-FD8082FA4DFF</segment>
<tableSpace>F77AAD8B-698F-5207-6B5F-A30E25666E1A</tableSpace>
</IndexProxy>
<IndexProxy class="oracle.dbtools.crest.model.design.storage.oracle.v10g.IndexProxyOraclev10g" name="ANLAS_PK" id="BAE246D4-09A2-196A-9E51-41BD9E94DD3E">
<createdBy>johan</createdBy>
<createdTime>2023-02-21 09:17:52 UTC</createdTime>
<ownerDesignName>ERD</ownerDesignName>
<schemaObject>D9400E64-AD1A-8DFA-B7CC-565DC50367B8</schemaObject>
<segment>A5F15058-DD63-F951-4B2D-FD8082FA4DFF</segment>
<tableSpace>F77AAD8B-698F-5207-6B5F-A30E25666E1A</tableSpace>
</IndexProxy>
</indexProxies>
<foreignKeys>
<ForeignKey class="oracle.dbtools.crest.model.design.storage.oracle.v10g.FKProxyOraclev10g" name="ANLAS_ANLR_FK" id="1FB32010-9E8C-D33F-EF3D-EE698F0F5910">
<createdBy>johan</createdBy>
<createdTime>2023-02-21 09:17:52 UTC</createdTime>
<ownerDesignName>ERD</ownerDesignName>
</ForeignKey>
<ForeignKey class="oracle.dbtools.crest.model.design.storage.oracle.v10g.FKProxyOraclev10g" name="ANLAS_R_Q_FK" id="8025140B-42AE-D741-BD1F-0B72CC447886">
<createdBy>johan</createdBy>
<createdTime>2023-02-21 09:17:52 UTC</createdTime>
<ownerDesignName>ERD</ownerDesignName>
</ForeignKey>
<ForeignKey class="oracle.dbtools.crest.model.design.storage.oracle.v10g.FKProxyOraclev10g" name="ANLAS_R_SPH_FK" id="8F5319F0-7812-BD94-898B-B1F752EA88F2">
<createdBy>johan</createdBy>
<createdTime>2023-02-21 09:17:52 UTC</createdTime>
<ownerDesignName>ERD</ownerDesignName>
</ForeignKey>
<ForeignKey class="oracle.dbtools.crest.model.design.storage.oracle.v10g.FKProxyOraclev10g" name="ANLAS_R_PRQ_FK" id="988C7BC5-A079-1957-753C-DAD48296C785">
<createdBy>johan</createdBy>
<createdTime>2023-02-21 09:17:52 UTC</createdTime>
<ownerDesignName>ERD</ownerDesignName>
</ForeignKey>
<ForeignKey class="oracle.dbtools.crest.model.design.storage.oracle.v10g.FKProxyOraclev10g" name="ANLAS_PUOM_FK" id="A0B70054-CFF0-81D9-78BF-905F014DDF0B">
<createdBy>johan</createdBy>
<createdTime>2023-02-21 09:17:52 UTC</createdTime>
<ownerDesignName>ERD</ownerDesignName>
</ForeignKey>
<ForeignKey class="oracle.dbtools.crest.model.design.storage.oracle.v10g.FKProxyOraclev10g" name="ANLAS_PUOM_FK1" id="A202B5C0-5939-0484-81C3-CFFE099787F3">
<createdBy>johan</createdBy>
<createdTime>2023-02-21 09:17:52 UTC</createdTime>
<ownerDesignName>ERD</ownerDesignName>
</ForeignKey>
<ForeignKey class="oracle.dbtools.crest.model.design.storage.oracle.v10g.FKProxyOraclev10g" name="ANLAS_R_S_FK" id="B4DC769C-CD5E-901D-7427-1091BA3891CF">
<createdBy>johan</createdBy>
<createdTime>2023-02-21 09:17:52 UTC</createdTime>
<ownerDesignName>ERD</ownerDesignName>
</ForeignKey>
<ForeignKey class="oracle.dbtools.crest.model.design.storage.oracle.v10g.FKProxyOraclev10g" name="ANLAS_R_Q_FK2" id="CEC971D3-BAC7-690B-13F8-080F2659C620">
<createdBy>johan</createdBy>
<createdTime>2023-02-21 09:17:52 UTC</createdTime>
<ownerDesignName>ERD</ownerDesignName>
</ForeignKey>
<ForeignKey class="oracle.dbtools.crest.model.design.storage.oracle.v10g.FKProxyOraclev10g" name="ANLAS_ANLM_FK" id="D363D03A-EC2B-067E-4BB8-53242D9A35AE">
<createdBy>johan</createdBy>
<createdTime>2023-02-21 09:17:52 UTC</createdTime>
<ownerDesignName>ERD</ownerDesignName>
</ForeignKey>
<ForeignKey class="oracle.dbtools.crest.model.design.storage.oracle.v10g.FKProxyOraclev10g" name="ANLAS_R_SFT_FK" id="E24D6067-7479-4C3F-48B0-4075A3703720">
<createdBy>johan</createdBy>
<createdTime>2023-02-21 09:17:52 UTC</createdTime>
<ownerDesignName>ERD</ownerDesignName>
</ForeignKey>
</foreignKeys>
<primaryKeys>
<PrimaryKey class="oracle.dbtools.crest.model.design.storage.oracle.v10g.PKProxyOraclev10g" name="ANLAS_PK" id="89E291C9-D990-90B9-D41A-E998D659561F">
<createdBy>johan</createdBy>
<createdTime>2023-02-21 09:17:52 UTC</createdTime>
<ownerDesignName>ERD</ownerDesignName>
<segment>A5F15058-DD63-F951-4B2D-FD8082FA4DFF</segment>
<tableSpace>F77AAD8B-698F-5207-6B5F-A30E25666E1A</tableSpace>
<existingIndex>BAE246D4-09A2-196A-9E51-41BD9E94DD3E</existingIndex>
<indexSegment>A5F15058-DD63-F951-4B2D-FD8082FA4DFF</indexSegment>
<indexSort>SORTED</indexSort>
<usingIndex>BY INDEX NAME</usingIndex>
</PrimaryKey>
</primaryKeys>
<uniqueKeys>
<UniqueKey class="oracle.dbtools.crest.model.design.storage.oracle.v10g.UniqueOraclev10g" name="ANLAS_GUID" id="464364F6-B5B7-0E48-4B05-BAF3156116D8">
<createdBy>johan</createdBy>
<createdTime>2023-02-21 09:17:52 UTC</createdTime>
<ownerDesignName>ERD</ownerDesignName>
<segment>A5F15058-DD63-F951-4B2D-FD8082FA4DFF</segment>
<tableSpace>F77AAD8B-698F-5207-6B5F-A30E25666E1A</tableSpace>
<existingIndex>96D79C01-F913-AF6B-2ABD-7C2DC176B54E</existingIndex>
<indexSegment>A5F15058-DD63-F951-4B2D-FD8082FA4DFF</indexSegment>
<indexSort>SORTED</indexSort>
<usingIndex>BY INDEX NAME</usingIndex>
</UniqueKey>
</uniqueKeys>
</TableProxyOraclev12c>
